CHANGES.txt
MANIFEST.in
README.txt
requirements.txt
setup.py
docs/HISTORY.txt
wheelcms_valve/__init__.py
wheelcms_valve/models.py
wheelcms_valve.egg-info/PKG-INFO
wheelcms_valve.egg-info/SOURCES.txt
wheelcms_valve.egg-info/dependency_links.txt
wheelcms_valve.egg-info/namespace_packages.txt
wheelcms_valve.egg-info/not-zip-safe
wheelcms_valve.egg-info/requires.txt
wheelcms_valve.egg-info/top_level.txt
wheelcms_valve/management/__init__.py
wheelcms_valve/management/commands/__init__.py
wheelcms_valve/management/commands/convert_wxr.py
wheelcms_valve/static/css/wheelcms_valve.css
wheelcms_valve/static/img/icons/blogs.png
wheelcms_valve/static/img/icons/rss_add.png
wheelcms_valve/templates/wheelcms_valve/valveblog_view.html
wheelcms_valve/templates/wheelcms_valve/valveentry_detail.html
wheelcms_valve/templates/wheelcms_valve/valveentry_view.html
wheelcms_valve/tests/__init__.py
wheelcms_valve/tests/conftest.py
wheelcms_valve/tests/test_context.py
wheelcms_valve/tests/test_valvetypes.py