Metadata-Version: 1.1
Name: wheelcms-valve
Version: 0.9
Summary: A blogging application for WheelCMS
Home-page: http://github.com/wheelcms/wheelcms_valve
Author: Ivo van der Wijk
Author-email: wheelcms@in.m3r.nl
License: BSD
Platform: UNKNOWN
Classifier: Programming Language :: Python
